setup.cfg
setup.py
authform_middleware/__init__.py
authform_middleware/authform.py
authform_middleware.egg-info/PKG-INFO
authform_middleware.egg-info/SOURCES.txt
authform_middleware.egg-info/dependency_links.txt
authform_middleware.egg-info/requires.txt
authform_middleware.egg-info/top_level.txt