Metadata-Version: 1.0
Name: authform_middleware
Version: 0.2.3
Summary: Form authentication middleware for WSGI applications
Home-page: http://bitbucket.org/Dalius/authform-middleware/
Author: Dalius Dobravolskas
Author-email: dalius.dobravolskas@gmail.com
License: MIT
Platform: UNKNOWN
